blurb/__init__.py
blurb/__main__.py
blurb/_version.py
blurb/blurb.py
blurb-1.3.0.dist-info/METADATA
blurb-1.3.0.dist-info/WHEEL
blurb-1.3.0.dist-info/entry_points.txt
blurb-1.3.0.dist-info/licenses/LICENSE.txt
blurb-1.3.0.dist-info/RECORD
