Metadata-Version: 2.3
Name: blurb
Version: 1.3.0
Summary: Command-line tool to manage CPython Misc/NEWS.d entries.
Project-URL: Changelog, https://github.com/python/blurb/blob/main/CHANGELOG.md
Project-URL: Homepage, https://github.com/python/blurb
Project-URL: Source, https://github.com/python/blurb
Author-email: Larry Hastings <larry@hastings.org>
Maintainer-email: Python Core Developers <core-workflow@mail.python.org>
License-File: LICENSE.txt
Classifier: Intended Audience :: Developers
Classifier: License :: OSI Approved :: BSD License
Classifier: Programming Language :: Python :: 3 :: Only
Classifier: Programming Language :: Python :: 3.9
Classifier: Programming Language :: Python :: 3.10
Classifier: Programming Language :: Python :: 3.11
Classifier: Programming Language :: Python :: 3.12
Classifier: Programming Language :: Python :: 3.13
Requires-Python: >=3.9
Provides-Extra: tests
Requires-Dist: pyfakefs; extra == 'tests'
Requires-Dist: pytest; extra == 'tests'
Requires-Dist: pytest-cov; extra == 'tests'
